{
	"backgrounds": [
		"levels_map_bg_3",
		"levels_map_bg_2",
		"levels_map_bg_1"
	],
	"level_icons": [
		{
			"level_number": 1,
			"x": 370.93,
			"y": 6030.26
		},
		{
			"level_number": 2,
			"x": 443.7,
			"y": 5895.83
		},
		{
			"level_number": 3,
			"x": 589.25,
			"y": 5706.83
		},
		{
			"level_number": 4,
			"x": 499.29,
			"y": 5486.5
		},
		{
			"level_number": 5,
			"x": 272.89,
			"y": 5427.88
		},
		{
			"level_number": 6,
			"x": 343.64,
			"y": 5212.6
		},
		{
			"level_number": 7,
			"x": 528.6,
			"y": 5069.08
		},
		{
			"level_number": 8,
			"x": 275.92,
			"y": 4926.57
		},
		{
			"level_number": 9,
			"x": 262.79,
			"y": 4674.91
		},
		{
			"level_number": 10,
			"x": 515.46,
			"y": 4698.15
		},
		{
			"level_number": 11,
			"x": 544.78,
			"y": 4456.59
		},
		{
			"level_number": 12,
			"x": 421.47,
			"y": 4325.21
		},
		{
			"level_number": 13,
			"x": 364.87,
			"y": 4172.59
		},
		{
			"level_number": 14,
			"x": 359.81,
			"y": 3985.61
		},
		{
			"level_number": 15,
			"x": 481.1,
			"y": 3854.22
		},
		{
			"level_number": 16,
			"x": 538.71,
			"y": 3678.35
		},
		{
			"level_number": 17,
			"x": 545.79,
			"y": 3431.75
		},
		{
			"level_number": 18,
			"x": 401.25,
			"y": 3272.05
		},
		{
			"level_number": 19,
			"x": 264.81,
			"y": 3134.61
		},
		{
			"level_number": 20,
			"x": 493.23,
			"y": 3088.11
		},
		{
			"level_number": 21,
			"x": 473.02,
			"y": 2908.2
		},
		{
			"level_number": 22,
			"x": 210.23,
			"y": 2834.43
		},
		{
			"level_number": 23,
			"x": 281.99,
			"y": 2625.21
		},
		{
			"level_number": 24,
			"x": 539.72,
			"y": 2657.55
		},
		{
			"level_number": 25,
			"x": 470.99,
			"y": 2426.1
		},
		{
			"level_number": 26,
			"x": 386.1,
			"y": 2280.56
		},
		{
			"level_number": 27,
			"x": 371.95,
			"y": 2130.98
		},
		{
			"level_number": 28,
			"x": 367.9,
			"y": 1955.12
		},
		{
			"level_number": 29,
			"x": 466.95,
			"y": 1795.42
		},
		{
			"level_number": 30,
			"x": 582.17,
			"y": 1568.02
		},
		{
			"level_number": 31,
			"x": 433.6,
			"y": 1397.21
		},
		{
			"level_number": 32,
			"x": 213.26,
			"y": 1269.86
		},
		{
			"level_number": 33,
			"x": 370.93,
			"y": 1120.28
		},
		{
			"level_number": 34,
			"x": 516.48,
			"y": 967.66
		},
		{
			"level_number": 35,
			"x": 353.75,
			"y": 861.54
		},
		{
			"level_number": 36,
			"x": 172.83,
			"y": 683.65
		},
		{
			"level_number": 37,
			"x": 364.87,
			"y": 538.71
		},
		{
			"level_number": 38,
			"x": 563.98,
			"y": 493.22
		},
		{
			"level_number": 39,
			"x": 511.42,
			"y": 341.61
		},
		{
			"level_number": 40,
			"x": 385.08,
			"y": 228.42
		}
	],
	"decor": [
		{
			"type": "fox_in_hole",
			"x": 360,
			"y": 2960
		},
		{
			"type": "fox",
			"x": 430,
			"y": 5380
		},
		{
			"type": "fire",
			"x": 176.87,
			"y": 5789.24
		},
		{
			"type": "cloud",
			"frame": "decor/clouds/cloud_1_01",
			"x": 63.07568355189849,
			"y": 5537.22569652613
		},
		{
			"type": "cloud",
			"frame": "decor/clouds/cloud_1_02",
			"x": 673.7663495328705,
			"y": 4973.29922415399
		},
		{
			"type": "cloud",
			"frame": "decor/clouds/cloud_1_03",
			"x": 144.60752549927145,
			"y": 4280.340564683414
		},
		{
			"type": "cloud",
			"frame": "decor/clouds/cloud_2_01",
			"x": 263.3095054427017,
			"y": 3582.919284502698
		},
		{
			"type": "cloud",
			"frame": "decor/clouds/cloud_2_02",
			"x": 277.61995371560806,
			"y": 2875.893113338472
		},
		{
			"type": "cloud",
			"frame": "decor/clouds/cloud_2_03",
			"x": 601.4886431816235,
			"y": 2184.9413410450466
		},
		{
			"type": "cloud",
			"frame": "decor/clouds/cloud_3_01",
			"x": 213.77629210593983,
			"y": 1488.2717548204255
		},
		{
			"type": "cloud",
			"frame": "decor/clouds/cloud_3_02",
			"x": 352.18102339933154,
			"y": 974.3536545891224
		},
		{
			"type": "cloud",
			"frame": "decor/clouds/cloud_3_03",
			"x": 562.7372932201938,
			"y": 375.8705278848625
		}
	]
}
